remote_wheel/__init__.py
remote_wheel/py.typed
remote_wheel-0.2.0.dist-info/LICENSE
remote_wheel-0.2.0.dist-info/METADATA
remote_wheel-0.2.0.dist-info/WHEEL
remote_wheel-0.2.0.dist-info/entry_points.txt
remote_wheel-0.2.0.dist-info/RECORD
