Metadata-Version: 2.1
Name: remote-wheel
Version: 0.2.0
Summary: Access files from a remote wheel.
Author-email: Dominic Davis-Foster <dominic@davis-foster.co.uk>
License: MIT
Keywords: dist-info,http-range,metadata,pep427,pypi,wheel
Home-page: https://github.com/repo-helper/remote-wheel
Project-URL: Issue Tracker, https://github.com/repo-helper/remote-wheel/issues
Project-URL: Source Code, https://github.com/repo-helper/remote-wheel
Project-URL: Documentation, https://remote-wheel.readthedocs.io/en/latest
Platform: Windows
Platform: macOS
Platform: Linux
Classifier: Development Status :: 4 - Beta
Classifier: Intended Audience :: Developers
Classifier: License :: OSI Approved :: MIT License
Classifier: Operating System :: OS Independent
Classifier: Programming Language :: Python
Classifier: Programming Language :: Python :: 3 :: Only
Classifier: Programming Language :: Python :: 3.7
Classifier: Programming Language :: Python :: 3.8
Classifier: Programming Language :: Python :: 3.9
Classifier: Programming Language :: Python :: 3.10
Classifier: Programming Language :: Python :: 3.11
Classifier: Programming Language :: Python :: Implementation :: CPython
Classifier: Programming Language :: Python :: Implementation :: PyPy
Classifier: Topic :: Software Development :: Libraries :: Python Modules
Classifier: Topic :: System :: Archiving :: Packaging
Classifier: Typing :: Typed
Requires-Python: >=3.7
Requires-Dist: apeye>=1.1.0
Requires-Dist: dist-meta>=0.3.0
Requires-Dist: handy-archives>=0.1.0
Requires-Dist: packaging>=21.0
Requires-Dist: remotezip>=0.12.1
Requires-Dist: requests>=2.26.0
